lifelogger_ai/__init__.py
lifelogger_ai/main.py
lifelogger_ai/prompts.py
lifelogger_ai-2025.12.21160026.dist-info/METADATA
lifelogger_ai-2025.12.21160026.dist-info/WHEEL
lifelogger_ai-2025.12.21160026.dist-info/top_level.txt
lifelogger_ai-2025.12.21160026.dist-info/RECORD
