Metadata-Version: 2.4
Name: lifelogger-ai
Version: 2025.12.21160026
Summary: A new package that helps users capture and organize their life moments in a structured way. Users can input their experiences, thoughts, or significant events, and the package will process this text t
Author-email: lifelogger-ai <hi@eugene.plus>
License: MIT
Project-URL: Homepage, https://github.com/chigwell/lifelogger-ai
Requires-Python: >=3.9
Requires-Dist: langchain-llm7>=0.0.0
Requires-Dist: llmatch-messages>=0.0.0
Requires-Dist: langchain-core>=0.3.0
